fdeb/__init__.py
fdeb/fdeb.py
fdeb-0.0.2.dist-info/LICENSE
fdeb-0.0.2.dist-info/METADATA
fdeb-0.0.2.dist-info/WHEEL
fdeb-0.0.2.dist-info/top_level.txt
fdeb-0.0.2.dist-info/RECORD
